ctfr/methods_dict.py
ctfr/exception.py
ctfr/__init__.py
ctfr/warning.py
ctfr/meta.py
ctfr/methods/__init__.py
ctfr/core/core_utils.py
ctfr/core/__init__.py
ctfr/core/ctfr.py
ctfr/core/ctfr_from_specs.py
ctfr/utils/arguments_check.py
ctfr/utils/methods.py
ctfr/utils/__init__.py
ctfr/utils/audio.py
ctfr/utils/private.py
ctfr/utils/data.py
ctfr/implementations/binwise_simple.py
ctfr/implementations/swgm_cy.cpython-312-darwin.so
ctfr/implementations/sls_h_cy.pyx
ctfr/implementations/__init__.py
ctfr/implementations/sls_i_cy.c
ctfr/implementations/sls_h_cy.cpython-312-darwin.so
ctfr/implementations/lt_cy.pyx
ctfr/implementations/swgm_cy.c
ctfr/implementations/lt_cy.c
ctfr/implementations/sls_h_cy.c
ctfr/implementations/fls_cy.pyx
ctfr/implementations/lt_cy.cpython-312-darwin.so
ctfr/implementations/sls_i_cy.pyx
ctfr/implementations/fls_cy.cpython-312-darwin.so
ctfr/implementations/fls_cy.c
ctfr/implementations/swgm_cy.pyx
ctfr/implementations/sls_i_cy.cpython-312-darwin.so
ctfr-0.1.0.dist-info/RECORD
ctfr-0.1.0.dist-info/WHEEL
ctfr-0.1.0.dist-info/top_level.txt
ctfr-0.1.0.dist-info/METADATA
ctfr-0.1.0.dist-info/licenses/LICENSE
