Metadata-Version: 2.4
Name: ctfr
Version: 0.1.0
Summary: Package for efficiently computing combined time-frequency representations of audio signals.
Author: Bernardo A. Boechat, Luiz W. P. Biscainho, Maurício do V. M. da Costa
License-Expression: MIT
Project-URL: Homepage, https://github.com/b-boechat/ctfr
Project-URL: Issues, https://github.com/b-boechat/ctfr/issues
Project-URL: Documentation, https://ctfr.readthedocs.io/en/latest/
Keywords: audio,music,sound,music information retrieval,time-frequency representations
Classifier: Programming Language :: Python :: 3 :: Only
Classifier: Development Status :: 3 - Alpha
Classifier: Operating System :: POSIX :: Linux
Classifier: Operating System :: Microsoft :: Windows
Classifier: Operating System :: MacOS
Classifier: Programming Language :: Cython
Classifier: Programming Language :: Python :: 3.10
Classifier: Programming Language :: Python :: 3.11
Classifier: Programming Language :: Python :: 3.12
Classifier: Topic :: Multimedia :: Sound/Audio
Requires-Python: >=3.10
License-File: LICENSE
Requires-Dist: numpy
Requires-Dist: librosa
Requires-Dist: scipy
Requires-Dist: pooch
Provides-Extra: dev
Requires-Dist: cython>=3; extra == "dev"
Requires-Dist: setuptools>=69; extra == "dev"
Requires-Dist: pip>=24; extra == "dev"
Requires-Dist: matplotlib>=3.3; extra == "dev"
Provides-Extra: display
Requires-Dist: matplotlib>=3.3; extra == "display"
Dynamic: license-file
